gpioserver/__init__.py
gpioserver/__main__.py
gpioserver/app.py
gpioserver/cli.py
gpioserver/gpio.py
gpioserver-1.0.4.dist-info/METADATA
gpioserver-1.0.4.dist-info/WHEEL
gpioserver-1.0.4.dist-info/entry_points.txt
gpioserver-1.0.4.dist-info/top_level.txt
gpioserver-1.0.4.dist-info/RECORD
